htmlxify/__init__.py
htmlxify/cli.py
htmlxify/generators/__init__.py
htmlxify/generators/css_gen.py
htmlxify/generators/html_gen.py
htmlxify/generators/js_gen.py
htmlxify/parser/__init__.py
htmlxify/parser/ast_builder.py
htmlxify/parser/grammar.lark
htmlxify/parser/indent_processor.py
htmlxify/utils/__init__.py
htmlxify/validator/__init__.py
htmlxify/validator/semantic.py
htmlxify-1.0.0.dist-info/licenses/LICENSE
htmlxify-1.0.0.dist-info/METADATA
htmlxify-1.0.0.dist-info/WHEEL
htmlxify-1.0.0.dist-info/entry_points.txt
htmlxify-1.0.0.dist-info/top_level.txt
htmlxify-1.0.0.dist-info/RECORD
