Metadata-Version: 2.4
Name: htmlxify
Version: 1.0.0
Summary: htmlxify - A simplified web markup language compiler that transpiles to HTML, CSS, and JavaScript
Home-page: https://github.com/Aquib489/htmlxify
Author: Aquib489
Author-email: aquib.gaming9@gmail.com
License: GPL-3.0
Keywords: html compiler web markup transpiler htmlxify
Classifier: Development Status :: 4 - Beta
Classifier: Intended Audience :: Developers
Classifier: Topic :: Software Development :: Compilers
Classifier: License :: OSI Approved :: GNU General Public License v3 (GPLv3)
Classifier: Programming Language :: Python :: 3
Classifier: Programming Language :: Python :: 3.8
Classifier: Programming Language :: Python :: 3.9
Classifier: Programming Language :: Python :: 3.10
Classifier: Programming Language :: Python :: 3.11
Classifier: Programming Language :: Python :: 3.12
Requires-Python: >=3.8
License-File: LICENSE
Requires-Dist: attrs==25.4.0
Requires-Dist: black==23.12.1
Requires-Dist: cattrs==25.3.0
Requires-Dist: click==8.3.0
Requires-Dist: colorama==0.4.6
Requires-Dist: coverage==7.11.2
Requires-Dist: cssbeautifier==1.15.4
Requires-Dist: EditorConfig==0.17.1
Requires-Dist: iniconfig==2.3.0
Requires-Dist: jsbeautifier==1.15.4
Requires-Dist: lark==1.1.9
Requires-Dist: lsprotocol==2023.0.1
Requires-Dist: mypy==1.7.1
Requires-Dist: mypy_extensions==1.1.0
Requires-Dist: packaging==25.0
Requires-Dist: pathspec==0.12.1
Requires-Dist: platformdirs==4.5.0
Requires-Dist: pluggy==1.6.0
Requires-Dist: pygls==1.3.0
Requires-Dist: pytest==7.4.3
Requires-Dist: pytest-cov==4.1.0
Requires-Dist: six==1.17.0
Requires-Dist: sourcemap==0.2.1
Requires-Dist: tinycss2==1.2.1
Requires-Dist: typing_extensions==4.15.0
Requires-Dist: webencodings==0.5.1
Dynamic: author
Dynamic: author-email
Dynamic: classifier
Dynamic: description
Dynamic: description-content-type
Dynamic: home-page
Dynamic: keywords
Dynamic: license
Dynamic: license-file
Dynamic: requires-dist
Dynamic: requires-python
Dynamic: summary
